pwhtmltopdf-0.2.0.dist-info/METADATA
pwhtmltopdf-0.2.0.dist-info/WHEEL
pwhtmltopdf-0.2.0.dist-info/licenses/LICENSE
pwhtmltopdf/__init__.py
pwhtmltopdf/abc.py
pwhtmltopdf/core.py
pwhtmltopdf/pw.py
pwhtmltopdf/py.typed
pwhtmltopdf/structures.py
pwhtmltopdf/types.py
pwhtmltopdf-0.2.0.dist-info/RECORD
