Metadata-Version: 2.1
Name: pwhtmltopdf
Version: 0.2.0
Summary: playwright render html to pdf
Keywords: playwright html pdf
Home-page: https://github.com/vvanglro/pwhtmltopdf
Author-Email: vvanglro <vvanglro@gmail.com>
License: Apache-2.0
Classifier: Topic :: Software Development :: Libraries :: Python Modules
Classifier: Programming Language :: Python :: 3
Classifier: Programming Language :: Python :: 3 :: Only
Classifier: Programming Language :: Python :: 3.8
Classifier: Programming Language :: Python :: 3.9
Classifier: Programming Language :: Python :: 3.10
Classifier: Programming Language :: Python :: 3.11
Classifier: Programming Language :: Python :: 3.12
Project-URL: Homepage, https://github.com/vvanglro/pwhtmltopdf
Project-URL: Repository, https://github.com/vvanglro/pwhtmltopdf.git
Project-URL: Documentation, https://github.com/vvanglro/pwhtmltopdf
Requires-Python: <4.0,>=3.8
Requires-Dist: playwright
Requires-Dist: jinja2<4.0.0,>=3.1.2
